<annotation>
	<folder>images</folder>
	<filename>31DM1qejh1L.jpg</filename>
	<path>A:\ML Projects\ML\images\31DM1qejh1L.jpg</path>
	<source>
		<database>Unknown</database>
	</source>
	<size>
		<width>1003</width>
		<height>1003</height>
		<depth>{'level': [1, 2, 3, 4, 5, 5, 2, 3, 4, 5, 5, 5, 5, 2, 3, 4, 5], 'page_num': [1, 1, 1, 1, 1, 1, 1, 1, 1, 1, 1, 1, 1, 1, 1, 1, 1], 'block_num': [0, 1, 1, 1, 1, 1, 2, 2, 2, 2, 2, 2, 2, 3, 3, 3, 3], 'par_num': [0, 0, 1, 1, 1, 1, 0, 1, 1, 1, 1, 1, 1, 0, 1, 1, 1], 'line_num': [0, 0, 0, 1, 1, 1, 0, 0, 1, 1, 1, 1, 1, 0, 0, 1, 1], 'word_num': [0, 0, 0, 0, 1, 2, 0, 0, 0, 1, 2, 3, 4, 0, 0, 0, 1], 'left': [0, 318, 318, 318, 318, 377, 567, 567, 567, 567, 612, 660, 703, 268, 268, 268, 268], 'top': [0, 319, 319, 319, 320, 319, 510, 510, 510, 510, 510, 510, 514, 380, 380, 380, 380], 'width': [1003, 160, 160, 160, 49, 101, 168, 168, 168, 35, 37, 33, 32, 258, 258, 258, 258], 'height': [1003, 25, 25, 25, 20, 25, 24, 24, 24, 21, 24, 21, 16, 304, 304, 304, 304], 'conf': [-1, -1, -1, -1, 80, 63, -1, -1, -1, 83, 75, 75, 75, -1, -1, -1, 95], 'text': ['', '', '', '', '0.39', 'in/1icm', '', '', '', '0.7', 'in/', '1.8', 'cm', '', '', '', '']}</depth>
	</size>
	<segmented>0</segmented>
	<object>
		<name>0.39</name>
		<pose>Unspecified</pose>
		<truncated>0</truncated>
		<difficult>0</difficult>
		<bndbox>
			<xmin>318</xmin>
			<ymin>320</ymin>
			<xmax>367</xmax>
			<ymax>340</ymax>
		</bndbox>
	</object>
	<object>
		<name>in/1icm</name>
		<pose>Unspecified</pose>
		<truncated>0</truncated>
		<difficult>0</difficult>
		<bndbox>
			<xmin>377</xmin>
			<ymin>319</ymin>
			<xmax>478</xmax>
			<ymax>344</ymax>
		</bndbox>
	</object>
	<object>
		<name>0.7</name>
		<pose>Unspecified</pose>
		<truncated>0</truncated>
		<difficult>0</difficult>
		<bndbox>
			<xmin>567</xmin>
			<ymin>510</ymin>
			<xmax>602</xmax>
			<ymax>531</ymax>
		</bndbox>
	</object>
	<object>
		<name>in/</name>
		<pose>Unspecified</pose>
		<truncated>0</truncated>
		<difficult>0</difficult>
		<bndbox>
			<xmin>612</xmin>
			<ymin>510</ymin>
			<xmax>649</xmax>
			<ymax>534</ymax>
		</bndbox>
	</object>
	<object>
		<name>1.8</name>
		<pose>Unspecified</pose>
		<truncated>0</truncated>
		<difficult>0</difficult>
		<bndbox>
			<xmin>660</xmin>
			<ymin>510</ymin>
			<xmax>693</xmax>
			<ymax>531</ymax>
		</bndbox>
	</object>
	<object>
		<name>cm</name>
		<pose>Unspecified</pose>
		<truncated>0</truncated>
		<difficult>0</difficult>
		<bndbox>
			<xmin>703</xmin>
			<ymin>514</ymin>
			<xmax>735</xmax>
			<ymax>530</ymax>
		</bndbox>
	</object>
</annotation>
