<annotation>
	<folder>images</folder>
	<filename>31i8HJcQjJL.jpg</filename>
	<path>A:\ML Projects\ML\images\31i8HJcQjJL.jpg</path>
	<source>
		<database>Unknown</database>
	</source>
	<size>
		<width>400</width>
		<height>400</height>
		<depth>{'level': [1, 2, 3, 4, 5, 2, 3, 4, 5, 5, 5, 5, 5, 2, 3, 4, 5, 2, 3, 4, 5, 4, 5, 2, 3, 4, 5], 'page_num': [1, 1, 1, 1, 1, 1, 1, 1, 1, 1, 1, 1, 1, 1, 1, 1, 1, 1, 1, 1, 1, 1, 1, 1, 1, 1, 1], 'block_num': [0, 1, 1, 1, 1, 2, 2, 2, 2, 2, 2, 2, 2, 3, 3, 3, 3, 4, 4, 4, 4, 4, 4, 5, 5, 5, 5], 'par_num': [0, 0, 1, 1, 1, 0, 1, 1, 1, 1, 1, 1, 1, 0, 1, 1, 1, 0, 1, 1, 1, 1, 1, 0, 1, 1, 1], 'line_num': [0, 0, 0, 1, 1, 0, 0, 1, 1, 1, 1, 1, 1, 0, 0, 1, 1, 0, 0, 1, 1, 2, 2, 0, 0, 1, 1], 'word_num': [0, 0, 0, 0, 1, 0, 0, 0, 1, 2, 3, 4, 5, 0, 0, 0, 1, 0, 0, 0, 1, 0, 1, 0, 0, 0, 1], 'left': [0, 213, 213, 213, 213, 27, 27, 27, 27, 67, 91, 147, 203, 88, 88, 88, 88, 111, 111, 111, 111, 113, 113, 18, 18, 18, 18], 'top': [0, 0, 0, 0, 0, 121, 121, 121, 121, 150, 147, 152, 161, 198, 198, 198, 198, 224, 224, 224, 224, 249, 249, 280, 280, 280, 280], 'width': [400, 131, 131, 131, 131, 185, 185, 185, 32, 12, 45, 12, 9, 76, 76, 76, 76, 29, 29, 29, 29, 26, 26, 194, 194, 194, 194], 'height': [400, 81, 81, 81, 81, 64, 64, 64, 64, 11, 18, 12, 7, 18, 18, 18, 18, 35, 35, 20, 20, 10, 10, 94, 94, 94, 94], 'conf': [-1, -1, -1, -1, 95, -1, -1, -1, 48, 94, 25, 79, 23, -1, -1, -1, 13, -1, -1, -1, 68, -1, 62, -1, -1, -1, 95], 'text': ['', '', '', '', ' ', '', '', '', 'I', '+', 'FS', '+', '.', '', '', '', '—S——', '', '', '', ')', '', '24G', '', '', '', '']}</depth>
	</size>
	<segmented>0</segmented>
	<object>
		<name>+</name>
		<pose>Unspecified</pose>
		<truncated>0</truncated>
		<difficult>0</difficult>
		<bndbox>
			<xmin>67</xmin>
			<ymin>150</ymin>
			<xmax>79</xmax>
			<ymax>161</ymax>
		</bndbox>
	</object>
	<object>
		<name>+</name>
		<pose>Unspecified</pose>
		<truncated>0</truncated>
		<difficult>0</difficult>
		<bndbox>
			<xmin>147</xmin>
			<ymin>152</ymin>
			<xmax>159</xmax>
			<ymax>164</ymax>
		</bndbox>
	</object>
	<object>
		<name>)</name>
		<pose>Unspecified</pose>
		<truncated>0</truncated>
		<difficult>0</difficult>
		<bndbox>
			<xmin>111</xmin>
			<ymin>224</ymin>
			<xmax>140</xmax>
			<ymax>244</ymax>
		</bndbox>
	</object>
	<object>
		<name>24G</name>
		<pose>Unspecified</pose>
		<truncated>0</truncated>
		<difficult>0</difficult>
		<bndbox>
			<xmin>113</xmin>
			<ymin>249</ymin>
			<xmax>139</xmax>
			<ymax>259</ymax>
		</bndbox>
	</object>
</annotation>
